eam_db_helper/__init__.py
eam_db_helper/db.py
eam_db_helper-0.0.6.dist-info/METADATA
eam_db_helper-0.0.6.dist-info/WHEEL
eam_db_helper-0.0.6.dist-info/licenses/LICENSE
eam_db_helper-0.0.6.dist-info/RECORD
