Metadata-Version: 2.3
Name: eam_db_helper
Version: 0.0.6
Summary: A package to interact with ms graph /users functionality
Author-email: Dave Gunn <daveg@8amsolutions.com>, Chase Churla <chasec@8amsolutions.com>
License-File: LICENSE
Classifier: License :: OSI Approved :: MIT License
Classifier: Operating System :: OS Independent
Classifier: Programming Language :: Python :: 3
Requires-Python: >=3.8
